[{"zip":3038,"cty":"Kirchlindach","reg":"BE"},{"zip":3116,"cty":"Kirchdorf BE","reg":"BE"},{"zip":3122,"cty":"Kehrsatz","reg":"BE"},{"zip":3210,"cty":"Kerzers","reg":"FR"},{"zip":3315,"cty":"Kräiligen","reg":"BE"},{"zip":3510,"cty":"Konolfingen","reg":"BE"},{"zip":3716,"cty":"Kandergrund","reg":"BE"},{"zip":3718,"cty":"Kandersteg","reg":"BE"},{"zip":3098,"cty":"Köniz","reg":"BE"},{"zip":3179,"cty":"Kriechenwil","reg":"BE"},{"zip":3723,"cty":"Kiental","reg":"BE"},{"zip":3216,"cty":"Ried b. Kerzers","reg":"FR"},{"zip":3283,"cty":"Kallnach","reg":"BE"},{"zip":3326,"cty":"Krauchthal","reg":"BE"},{"zip":3425,"cty":"Koppigen","reg":"BE"},{"zip":3704,"cty":"Krattigen","reg":"BE"},{"zip":3917,"cty":"Kippel","reg":"VS"},{"zip":3922,"cty":"Kalpetran","reg":"VS"},{"zip":4581,"cty":"Küttigkofen","reg":"SO"},{"zip":5054,"cty":"Kirchleerau-Moosleerau","reg":"AG"},{"zip":5314,"cty":"Kleindöttingen","reg":"AG"},{"zip":5444,"cty":"Künten","reg":"AG"},{"zip":5742,"cty":"Kölliken","reg":"AG"},{"zip":6047,"cty":"Kastanienbaum","reg":"LU"},{"zip":6056,"cty":"Kägiswil","reg":"OW"},{"zip":6213,"cty":"Knutwil","reg":"LU"},{"zip":6217,"cty":"Kottwil","reg":"LU"},{"zip":6234,"cty":"Kulmerau","reg":"LU"},{"zip":6277,"cty":"Kleinwangen","reg":"LU"},{"zip":6403,"cty":"Küssnacht am Rigi","reg":"SZ"},{"zip":7240,"cty":"Küblis","reg":"GR"},{"zip":8280,"cty":"Kreuzlingen 1","reg":"TG"},{"zip":8302,"cty":"Kloten","reg":"ZH"},{"zip":8307,"cty":"Ottikon b. Kemptthal","reg":"ZH"},{"zip":8314,"cty":"Kyburg","reg":"ZH"},{"zip":5466,"cty":"Kaiserstuhl AG","reg":"AG"},{"zip":8593,"cty":"Kesswil","reg":"TG"},{"zip":8750,"cty":"Klöntal","reg":"GL"},{"zip":8802,"cty":"Kilchberg ZH","reg":"ZH"},{"zip":8956,"cty":"Killwangen","reg":"AG"},{"zip":9622,"cty":"Krinau","reg":"SG"},{"zip":9214,"cty":"Kradolf","reg":"TG"},{"zip":8586,"cty":"Buch b. Kümmertshausen","reg":"TG"},{"zip":8109,"cty":"Kloster Fahr","reg":"AG"},{"zip":3823,"cty":"Kleine Scheidegg","reg":"BE"},{"zip":3629,"cty":"Kiesen","reg":"BE"},{"zip":3309,"cty":"Kernenried","reg":"BE"},{"zip":3413,"cty":"Kaltacker","reg":"BE"},{"zip":3713,"cty":"Reichenbach im Kandertal","reg":"BE"},{"zip":4245,"cty":"Kleinlützel","reg":"SO"},{"zip":4303,"cty":"Kaiseraugst","reg":"AG"},{"zip":5082,"cty":"Kaisten","reg":"AG"},{"zip":4566,"cty":"Kriegstetten","reg":"SO"},{"zip":4616,"cty":"Kappel SO","reg":"SO"},{"zip":4703,"cty":"Kestenholz","reg":"SO"},{"zip":5024,"cty":"Küttigen","reg":"AG"},{"zip":5313,"cty":"Klingnau","reg":"AG"},{"zip":5416,"cty":"Kirchdorf AG","reg":"AG"},{"zip":5625,"cty":"Kallern","reg":"AG"},{"zip":6010,"cty":"Kriens","reg":"LU"},{"zip":6010,"cty":"Pilatus Kulm","reg":"OW"},{"zip":6356,"cty":"Rigi Kaltbad","reg":"LU"},{"zip":6365,"cty":"Kehrsiten","reg":"NW"},{"zip":6410,"cty":"Rigi Klösterli","reg":"SZ"},{"zip":8259,"cty":"Kaltenbach","reg":"TG"},{"zip":8310,"cty":"Kemptthal","reg":"ZH"},{"zip":8451,"cty":"Kleinandelfingen","reg":"ZH"},{"zip":8700,"cty":"Küsnacht ZH","reg":"ZH"},{"zip":8926,"cty":"Kappel am Albis","reg":"ZH"},{"zip":9508,"cty":"Weingarten-Kalthäusern","reg":"TG"},{"zip":9533,"cty":"Kirchberg SG","reg":"SG"},{"zip":9642,"cty":"Ebnat-Kappel","reg":"SG"},{"zip":3283,"cty":"Niederried b. Kallnach","reg":"BE"},{"zip":4535,"cty":"Kammersrohr","reg":"SO"},{"zip":8546,"cty":"Kefikon TG","reg":"TG"},{"zip":6212,"cty":"Kaltbach","reg":"LU"},{"zip":9026,"cty":"St. Gallen Künzler AG","reg":"SG"},{"zip":6010,"cty":"Kriens 2","reg":"LU"},{"zip":8543,"cty":"Kefikon ZH","reg":"ZH"},{"zip":3071,"cty":"Ostermundigen KATA","reg":"BE"},{"zip":3098,"cty":"Schliern b. Köniz","reg":"BE"},{"zip":3126,"cty":"Kaufdorf","reg":"BE"},{"zip":3128,"cty":"Kirchenthurnen","reg":"BE"},{"zip":3273,"cty":"Kappelen","reg":"BE"},{"zip":3422,"cty":"Kirchberg BE","reg":"BE"},{"zip":4303,"cty":"Kaiseraugst Liebrüti","reg":"AG"},{"zip":4447,"cty":"Känerkinden","reg":"BL"},{"zip":4468,"cty":"Kienberg","reg":"SO"},{"zip":4496,"cty":"Kilchberg BL","reg":"BL"},{"zip":4586,"cty":"Kyburg-Buchegg","reg":"SO"},{"zip":4936,"cty":"Kleindietwil","reg":"BE"},{"zip":5054,"cty":"Kirchleerau","reg":"AG"},{"zip":5322,"cty":"Koblenz","reg":"AG"},{"zip":6064,"cty":"Kerns","reg":"OW"},{"zip":6410,"cty":"Rigi Kulm","reg":"SZ"},{"zip":7250,"cty":"Klosters","reg":"GR"},{"zip":7252,"cty":"Klosters Dorf","reg":"GR"},{"zip":8280,"cty":"Kreuzlingen","reg":"TG"},{"zip":8280,"cty":"Kreuzlingen 3","reg":"TG"},{"zip":8483,"cty":"Kollbrunn","reg":"ZH"},{"zip":8586,"cty":"Kümmertshausen","reg":"TG"},{"zip":8722,"cty":"Kaltbrunn","reg":"SG"},{"zip":8934,"cty":"Knonau","reg":"ZH"},{"zip":9451,"cty":"Kriessern","reg":"SG"},{"zip":9643,"cty":"Krummenau","reg":"SG"},{"zip":3213,"cty":"Kleinbösingen","reg":"FR"},{"zip":3212,"cty":"Kleingurmels","reg":"FR"},{"zip":8585,"cty":"Klarsreuti","reg":"TG"},{"zip":6011,"cty":"Kriens","reg":"LU"},{"zip":8510,"cty":"Frauenfeld Kant. Verwaltung","reg":"TG"},{"zip":8285,"cty":"Kreuzlingen Ifolor AG","reg":"TG"}]